tests/__init__.py
tests/conftest.py
tests/test_builds.py
tests/test_builds_response.py
tests/test_core.py
tests/test_helpers.py
tests/test_jobs.py
tests/test_nodes.py
tests/test_plugins.py
tests/test_queue.py
tests/test_system.py
tests/test_views.py
ujenkins/__init__.py
ujenkins/core.py
ujenkins/exceptions.py
ujenkins/helpers.py
ujenkins/py.typed
ujenkins/adapters/__init__.py
ujenkins/adapters/aio.py
ujenkins/adapters/sync.py
ujenkins/endpoints/__init__.py
ujenkins/endpoints/builds.py
ujenkins/endpoints/jobs.py
ujenkins/endpoints/nodes.py
ujenkins/endpoints/plugins.py
ujenkins/endpoints/queue.py
ujenkins/endpoints/system.py
ujenkins/endpoints/views.py
ujenkins-0.11.1.dist-info/LICENSE
ujenkins-0.11.1.dist-info/METADATA
ujenkins-0.11.1.dist-info/WHEEL
ujenkins-0.11.1.dist-info/top_level.txt
ujenkins-0.11.1.dist-info/RECORD
