Metadata-Version: 2.1
Name: ujenkins
Version: 0.11.1
Summary: Universal (sync/async) Python client for Jenkins
Home-page: https://github.com/pbelskiy/ujenkins
Download-URL: https://pypi.org/project/ujenkins
Author: Petr Belskiy
License: MIT
Keywords: jenkins
Classifier: Programming Language :: Python
Classifier: Programming Language :: Python :: 3
Classifier: Programming Language :: Python :: 3.8
Classifier: Programming Language :: Python :: 3.9
Classifier: Programming Language :: Python :: 3.10
Classifier: Programming Language :: Python :: 3.11
Classifier: Programming Language :: Python :: 3.12
Requires-Python: >=3.7
License-File: LICENSE
Requires-Dist: aiohttp~=3.6
Requires-Dist: requests~=2.24
Requires-Dist: urllib3<3,>=1.26
